[{"name":"死(2389619983)","time":"15:11:02","text":[" 来看看cod手柄"]},{"name":"手把爷（成年体）(766955124)","time":"15:15:10","text":["抽象"]},{"name":"死(2389619983)","time":"15:16:16","text":["确实抽象"]},{"name":"死(2389619983)","time":"15:16:20","text":["我看晕了"]},{"name":"手把爷（成年体）(766955124)","time":"15:16:38","text":["我本来感冒就晕了，看完之后更晕了"]},{"name":"手把爷（成年体）(766955124)","time":"15:16:40","img":["AF98CECC642C43fe812D39DF730C5018"]},{"name":"死(2389619983)","time":"15:17:31","text":["不建议学"]},{"name":"死(2389619983)","time":"15:17:35","text":["反正我学不来"]},{"name":"死(2389619983)","time":"15:17:38","img":["2429810E275745fbA4A5DBDF2078FDB2"]},{"name":"死(2389619983)","time":"15:17:57","text":["说起来你咋感冒的"]},{"name":"手把爷（成年体）(766955124)","time":"15:20:01","text":[" "]},{"name":"手把爷（成年体）(766955124)","time":"15:20:40","text":["他一打三"]},{"name":"手把爷（成年体）(766955124)","time":"15:20:42","img":["AF98CECC642C43fe812D39DF730C5018"]},{"name":"死(2389619983)","time":"15:21:08","text":["艹"]},{"name":"手把爷（成年体）(766955124)","time":"15:21:10","text":["也就晚点名还没开始站着说说话，第二天立马流皮涕加咳嗽"]},{"name":"手把爷（成年体）(766955124)","time":"15:21:40","text":["麻了"]},{"name":"手把爷（成年体）(766955124)","time":"16:32:04","text":[" 看在我感冒的份上"]},{"name":"手把爷（成年体）(766955124)","time":"16:32:09","text":["今晚打π吧"]},{"name":"手把爷（成年体）(766955124)","time":"16:32:13","img":["A4A1FEE49B7F45959F43DF917A7F5AFB.jpeg"]},{"name":"玩卡拉彼丘玩的(3345164105)","time":"16:37:55","img":["A1096A99E46448c88951717B75B68B23.jpeg"]},{"name":"玩卡拉彼丘玩的(3345164105)","time":"16:38:02","text":["6"]},{"name":"死(2389619983)","time":"18:36:09","text":["行"]},{"name":"死(2389619983)","time":"18:36:25","text":["我本来还说今晚没人陪我打π来着"]},{"name":"手把爷（成年体）(766955124)","time":"18:53:18","img":["AF98CECC642C43fe812D39DF730C5018"]},{"name":"手把爷（成年体）(766955124)","time":"18:53:23","text":[" 8点"]},{"name":"死(2389619983)","time":"18:53:30","text":["嗯"]},{"name":"手把爷（成年体）(766955124)","time":"20:02:01","text":[" 来？"]},{"name":"死(2389619983)","time":"20:03:28","text":["给我七分钟"]},{"name":"死(2389619983)","time":"20:03:33","text":["我把这个合约打了"]},{"name":"我在往里润(1193558074)","time":"22:46:21","img":["DBC583E419FE45a9A899057153309CC0"]},{"name":"我在往里润(1193558074)","time":"22:46:47","text":["北朝鲜向日本冲绳投导弹了"]},{"name":"我在往里润(1193558074)","time":"22:46:52","img":["6EBF7C30064D45159B4AECB7CBB06E47.jpeg"]},{"name":"我在往里润(1193558074)","time":"22:47:08","text":["好像是刚刚才发生的事"]},{"name":"我在往里润(1193558074)","time":"22:47:19","text":["10.46"]},{"name":"死(2389619983)","time":"22:55:17","text":["我这边的日本的朋友没有消息"]},{"name":"死(2389619983)","time":"22:55:20","img":["7EA6E789D25D43ccB104798362317889.jpeg"]},{"name":"我在往里润(1193558074)","time":"22:55:57","img":["6F409AB4C5844285BD40508F0F28A7CD.jpeg"]},{"name":"我在往里润(1193558074)","time":"22:55:59","text":["问问？"]},{"name":"手把爷（成年体）(766955124)","time":"22:56:22","img":["AF98CECC642C43fe812D39DF730C5018"]},{"name":"死(2389619983)","time":"23:01:28","text":[" 我这边辟谣了"]},{"name":"死(2389619983)","time":"23:01:31","img":["7EA6E789D25D43ccB104798362317889.jpeg"]},{"name":"我在往里润(1193558074)","time":"23:01:35","text":["那没事了"]},{"name":"死(2389619983)","time":"23:01:46","text":["三个人纷纷表示闻所未闻"]}]