[{"name":"死(2389619983)","time":"8:23:38","text":[" "]},{"name":"死(2389619983)","time":"8:23:53","text":["你有这种感觉"]},{"name":"我要成为怪A战碧高手(766955124)","time":"8:23:54","text":["6"]},{"name":"我要成为怪A战碧高手(766955124)","time":"8:24:01","text":["我看看"]},{"name":"我要成为怪A战碧高手(766955124)","time":"8:25:03","text":["没有吧"]},{"name":"快点让我怀孕QAQ(2975808627)","time":"8:25:21","img":["AE3771F363474a4fBFF931FF927A0511.jpeg"]},{"name":"死(2389619983)","time":"8:29:14","text":["有没有一种可能"]},{"name":"死(2389619983)","time":"8:29:18","text":["我们是土包子"]},{"name":"死(2389619983)","time":"8:29:35","img":["B88270E80C6D453dA61C33BE85F7AB90.jpeg"]},{"name":"死(2389619983)","time":"8:30:09","text":["反正我往市中心奔没有感觉"]},{"name":"死(2389619983)","time":"8:30:18","text":["夏天是真的"]},{"name":"快点让我怀孕QAQ(2975808627)","time":"8:37:42","text":[" 给我打米"]},{"name":"快点让我怀孕QAQ(2975808627)","time":"8:43:24","img":["55F1F74CF95845a38AC562A876EBADC7"]},{"name":"SwaniPeek(2579963328)","time":"10:25:07","img":["2404CC2E5F8C4186B532261B5CEAB13B"]},{"name":"快点让我怀孕QAQ(2975808627)","time":"11:17:04","text":["师傅真好van"]},{"name":"快点让我怀孕QAQ(2975808627)","time":"11:17:09","img":["051ED686CE8946f8A3678320B1C16EE4.jpeg"]},{"name":"SwaniPeek(2579963328)","time":"11:54:58","img":["4B1A4A6960224eaeBB006CF36749346A"]},{"name":"SwaniPeek(2579963328)","time":"12:01:00","img":["767B7977506643449E47174D40AF9A64.jpeg"]},{"name":"死(2389619983)","time":"17:30:53","text":["？"]},{"name":"死(2389619983)","time":"17:30:57","text":["起猛了"]},{"name":"死(2389619983)","time":"17:31:10","text":["看到APEX恶灵的本子了"]},{"name":"死(2389619983)","time":"17:31:21","text":["甚至是c102的"]},{"name":"晚来风急(2637813234)","time":"17:32:16","text":["？"]},{"name":"死(2389619983)","time":"17:35:15","text":["https://e-hentai.org/g/2696019/da957d0f6b/"]},{"name":"SwaniPeek(2579963328)","time":"17:35:24","img":["A4617968F53C4ab5884A89DC255A459F"]},{"name":"晚来风急(2637813234)","time":"17:48:42","img":["EE3FFECD862A4a0693AA56715D70055A"]},{"name":"死(2389619983)","time":"17:53:24","text":["？"],"img":["C67BC024F46E418c9E18F6CCA31CE5D7.jpeg","68F0A6FC075E4f5c9F4158C2551F02C1.jpeg","5EFE1C98ED1E42469633715506AFF690"]},{"name":"死(2389619983)","time":"17:53:43","text":["原来看完本子还要写论文的"]},{"name":"晚来风急(2637813234)","time":"17:54:30","text":["你的导就是对作品最好的认可"]},{"name":"快点让我怀孕QAQ(2975808627)","time":"18:41:16","img":["94CD30C929D14ed2ACD13AECD2ED22F9.jpeg"]},{"name":"快点让我怀孕QAQ(2975808627)","time":"18:41:19","text":["44"]},{"name":"快点让我怀孕QAQ(2975808627)","time":"18:41:21","img":["051ED686CE8946f8A3678320B1C16EE4.jpeg"]},{"name":"快点让我怀孕QAQ(2975808627)","time":"18:41:22","img":["4B1A4A6960224eaeBB006CF36749346A"]},{"name":"快点让我怀孕QAQ(2975808627)","time":"18:41:22","img":["16A59E5D5C9841adAE3D6F6B50F18690.jpeg"]},{"name":"快点让我怀孕QAQ(2975808627)","time":"18:41:28","text":["这一桌子四十四"]},{"name":"快点让我怀孕QAQ(2975808627)","time":"18:41:32","img":["C1C04C12821243b7A60AA73042736CD3"]},{"name":"兰.(513248092)","time":"18:43:21","text":["哪吃的"]},{"name":"兰.(513248092)","time":"18:43:22","text":["这么便宜"]},{"name":"兰.(513248092)","time":"18:43:25","text":["下次请我吃"]},{"name":"快点让我怀孕QAQ(2975808627)","time":"18:43:43","text":["湖经"]},{"name":"快点让我怀孕QAQ(2975808627)","time":"18:43:49","text":["二人餐"]},{"name":"快点让我怀孕QAQ(2975808627)","time":"18:43:54","text":["湖经学生证"]},{"name":"快点让我怀孕QAQ(2975808627)","time":"18:43:58","text":["半价"]},{"name":"快点让我怀孕QAQ(2975808627)","time":"18:44:00","img":["051ED686CE8946f8A3678320B1C16EE4.jpeg"]},{"name":"兰.(513248092)","time":"18:51:00","text":[" 下次请我吃"]},{"name":"快点让我怀孕QAQ(2975808627)","time":"18:51:23","img":["16A59E5D5C9841adAE3D6F6B50F18690.jpeg"]},{"name":"SwaniPeek(2579963328)","time":"18:53:24","img":["4B1A4A6960224eaeBB006CF36749346A"]},{"name":"玩卡拉彼丘玩的(3345164105)","time":"19:05:51","img":["8D08688F8764487b8890B0FECCFBABCD.jpeg"]},{"name":"玩卡拉彼丘玩的(3345164105)","time":"19:06:03","img":["194828B50CE74dbe919588E8735FFA74"]},{"name":"我要成为怪A战碧高手(766955124)","time":"19:06:43","text":["好耶"]},{"name":"我要成为怪A战碧高手(766955124)","time":"19:06:45","img":["B9CCFFBB2CD14f57BF45AB18CC164627.jpeg"]},{"name":"我要成为怪A战碧高手(766955124)","time":"19:06:57","text":[" 一会连麦打不"]},{"name":"兰.(513248092)","time":"19:07:00","img":["3B061B546D3541d8B6756F9C7BDD6D36.gif"]},{"name":"玩卡拉彼丘玩的(3345164105)","time":"19:07:21","text":["明天罢"]},{"name":"玩卡拉彼丘玩的(3345164105)","time":"19:07:27","text":["晚上约了瓦"]},{"name":"我要成为怪A战碧高手(766955124)","time":"19:07:29","img":["86A4E50DCD244fb3A8983709BDCCC305.jpeg"]},{"name":"玩卡拉彼丘玩的(3345164105)","time":"19:07:30","img":["061EB7B7C12E4a8aAB8C8A9A8E660A51"]},{"name":"我要成为怪A战碧高手(766955124)","time":"19:07:41","text":["彳亍"]},{"name":"玩卡拉彼丘玩的(3345164105)","time":"22:11:51","text":["我背两刀秒了"]},{"name":"玩卡拉彼丘玩的(3345164105)","time":"22:12:06","img":["69BDB14515914b9fB39314E62334FB00"]},{"name":"死(2389619983)","time":"22:15:49","text":["大树守卫？"]},{"name":"我要成为怪A战碧高手(766955124)","time":"22:17:09","text":["我在线"]},{"name":"我要成为怪A战碧高手(766955124)","time":"22:17:19","text":["要我来帮你揍他吗"]},{"name":"系统消息(10000)","time":"22:18:03","text":["我要成为怪A战碧高手撤回了一条消息，并坏笑了一下。"]},{"name":"我要成为怪A战碧高手(766955124)","time":"22:18:07","text":["刚把葛瑞克的神授塔找到"]},{"name":"晚来风急(2637813234)","time":"22:21:13","text":["你领他去盖利德晃一圈"]},{"name":"晚来风急(2637813234)","time":"22:21:31","text":["跟当地的毛茸茸大狗狗贴一贴"]},{"name":"兰.(513248092)","time":"22:26:18","text":["盖利德是吧"]},{"name":"玩卡拉彼丘玩的(3345164105)","time":"22:32:43","text":["那个大树守卫恁离谱啊"]},{"name":"我要成为怪A战碧高手(766955124)","time":"22:32:58","text":["这就不是给你刚出来打的"]},{"name":"玩卡拉彼丘玩的(3345164105)","time":"22:33:45","text":["啊"]},{"name":"兰.(513248092)","time":"22:33:46","text":[" 我来打"]},{"name":"玩卡拉彼丘玩的(3345164105)","time":"22:34:09","text":[" 怎么说"]},{"name":"我要成为怪A战碧高手(766955124)","time":"22:34:27","text":["采几片落叶花"]},{"name":"我要成为怪A战碧高手(766955124)","time":"22:34:32","text":["我来帮你"]},{"name":"我要成为怪A战碧高手(766955124)","time":"22:37:18","text":[" 你现在能联机不"]},{"name":"玩卡拉彼丘玩的(3345164105)","time":"22:37:53","text":["我有那个勾指"]},{"name":"我要成为怪A战碧高手(766955124)","time":"22:38:00","text":["ok"]},{"name":"我要成为怪A战碧高手(766955124)","time":"22:38:10","text":["那在赐福点画符"]},{"name":"玩卡拉彼丘玩的(3345164105)","time":"22:38:29","text":["怎么弄啊"]},{"name":"我要成为怪A战碧高手(766955124)","time":"22:38:36","text":["草"]},{"name":"我要成为怪A战碧高手(766955124)","time":"22:38:39","text":["直接电话"]},{"name":"我要成为怪A战碧高手(766955124)","time":"22:38:44","text":["打字麻烦"]},{"name":"死(2389619983)","time":"22:38:50","text":["是这样的"]},{"name":"玩卡拉彼丘玩的(3345164105)","time":"22:38:51","text":["明天罢"]},{"name":"玩卡拉彼丘玩的(3345164105)","time":"22:39:02","text":["要关电脑了"]},{"name":"死(2389619983)","time":"22:39:03","text":["前期如何解决大树守卫呢"]},{"name":"我要成为怪A战碧高手(766955124)","time":"22:39:09","text":["那行吧"]},{"name":"死(2389619983)","time":"22:39:09","text":["答案是不管他"]},{"name":"死(2389619983)","time":"22:39:11","text":["绕过去"]},{"name":"我要成为怪A战碧高手(766955124)","time":"22:39:26","text":["答案是叫一个通关的朋友扔卢恩和装备"]},{"name":"死(2389619983)","time":"22:39:39","text":["我没啥卢恩了"]},{"name":"我要成为怪A战碧高手(766955124)","time":"22:39:46","text":["我还有"]},{"name":"我要成为怪A战碧高手(766955124)","time":"22:39:48","text":["问题不大"]},{"name":"兰.(513248092)","time":"22:39:49","text":[" 关没"]},{"name":"兰.(513248092)","time":"22:40:02","text":["没关来我给你示范一遍"]},{"name":"玩卡拉彼丘玩的(3345164105)","time":"22:40:46","text":["怎么存档退啊"]},{"name":"我要成为怪A战碧高手(766955124)","time":"22:41:41","text":["自动存"]},{"name":"我要成为怪A战碧高手(766955124)","time":"22:41:53","text":["直接关游戏就行"]},{"name":"玩卡拉彼丘玩的(3345164105)","time":"22:42:37","text":["我看到了"]},{"name":"玩卡拉彼丘玩的(3345164105)","time":"22:42:39","img":["1B4A25EC248A49ce897370996DF7BD7E.jpeg"]},{"name":"兰.(513248092)","time":"22:42:53","text":["帅"]},{"name":"晚来风急(2637813234)","time":"22:45:44","text":[" 错的，骑马打可以无伤"]},{"name":"晚来风急(2637813234)","time":"22:46:09","text":["我和cno坐牢了一下午，最后我上马大棒单刷了"]},{"name":"晚来风急(2637813234)","time":"22:46:13","img":["B0702FE8DAED4005BB31D2F69D0C10B3.jpeg"]},{"name":"晚来风急(2637813234)","time":"22:46:26","text":["跟托雷特比起来门口大树超级呆"]},{"name":"兰.(513248092)","time":"22:47:19","text":[" 你玩的啥职业"]},{"name":"玩卡拉彼丘玩的(3345164105)","time":"22:48:33","text":["武士"]},{"name":"玩卡拉彼丘玩的(3345164105)","time":"22:48:36","img":["1B4A25EC248A49ce897370996DF7BD7E.jpeg"]},{"name":"我要成为怪A战碧高手(766955124)","time":"22:49:20","text":["果然"]},{"name":"兰.(513248092)","time":"22:49:28","text":["也还行"]},{"name":"兰.(513248092)","time":"22:49:42","text":["居然没玩轮椅法师"]},{"name":"兰.(513248092)","time":"22:49:44","img":["6ACAA163B028404594C60E665699FA51.gif"]},{"name":"玩卡拉彼丘玩的(3345164105)","time":"22:50:09","text":["玩太刀玩的"]},{"name":"兰.(513248092)","time":"23:08:15","text":["哈哈 没熄灯"]}]