[{"name":"玩卡拉彼丘玩的(3345164105)","time":"0:08:26","img":["C24523BCA3F2459cAAF817827D499A59.jpeg"]},{"name":"死(2389619983)","time":"0:31:07","img":["7612A7EA5DB84d02B63B4E733FD27385"]},{"name":"Swani(2579963328)","time":"0:50:40","text":[" 你开啊"]},{"name":"Swani(2579963328)","time":"0:50:44","text":["你倒是开夜市啊"]},{"name":"Swani(2579963328)","time":"0:50:45","text":["wxnm"]},{"name":"死(2389619983)","time":"0:57:53","text":["在破防中走向完结的物语"]},{"name":"我要成为怪A战碧高手(766955124)","time":"0:59:41","text":["不是破防，而是觉得我和瓦之间不适合"]},{"name":"我要成为怪A战碧高手(766955124)","time":"1:00:50","img":["38EA903F3A9C4f9fA3B48268012E56D1.jpeg"]},{"name":"Swani(2579963328)","time":"1:01:07","text":["那你试试cs2好不好"]},{"name":"我要成为怪A战碧高手(766955124)","time":"1:01:10","text":["这种射击模式不太适合"]},{"name":"Swani(2579963328)","time":"1:01:10","text":["没有狗"]},{"name":"Swani(2579963328)","time":"1:01:12","text":["没有云"]},{"name":"Swani(2579963328)","time":"1:01:18","text":["没有watch eyes"]},{"name":"Swani(2579963328)","time":"1:01:20","text":["没有鸟"]},{"name":"我要成为怪A战碧高手(766955124)","time":"1:01:20","text":["6"]},{"name":"Swani(2579963328)","time":"1:01:23","text":["没有炸弹"]},{"name":"Swani(2579963328)","time":"1:01:26","text":["没有火箭筒"]},{"name":"Swani(2579963328)","time":"1:01:29","text":["没有天基炮"]},{"name":"Swani(2579963328)","time":"1:01:42","text":["没有会虚空行走的小丑"]},{"name":"Swani(2579963328)","time":"1:01:46","text":["没有毒气"]},{"name":"Swani(2579963328)","time":"1:01:50","text":["没有墙"]},{"name":"Swani(2579963328)","time":"1:01:51","text":["来"]},{"name":"Swani(2579963328)","time":"1:01:57","text":["享受纯净的fps"]},{"name":"Swani(2579963328)","time":"1:02:07","text":["单纯的比反应 比定位 比枪法"]},{"name":"Swani(2579963328)","time":"1:02:14","text":["别逼我求你来玩cs2"]},{"name":"我要成为怪A战碧高手(766955124)","time":"1:02:15","img":["24789DDD7C524d6387333E0F5676A679.jpeg"]},{"name":"Swani(2579963328)","time":"1:02:17","img":["20B833C4A8B7498fA35D40752DE72F63"]},{"name":"Swani(2579963328)","time":"1:02:22","img":["514A7C3A87B545f090DC5ED89ADCF6A6.jpeg"]},{"name":"Swani(2579963328)","time":"1:02:27","text":["这就是cs2"]},{"name":"Swani(2579963328)","time":"1:02:31","img":["33FEFD811E444e4fBFDE7D72B3DFBB49"]},{"name":"我要成为怪A战碧高手(766955124)","time":"1:03:17","text":["那有瞬间一枪点头吗"]},{"name":"Swani(2579963328)","time":"1:03:38","text":["有呀"]},{"name":"Swani(2579963328)","time":"1:03:39","img":["F921AE942EFD466bAE8CA5423D24872F.jpeg"]},{"name":"Swani(2579963328)","time":"1:03:47","text":["你不喜欢被一枪头呀"]},{"name":"Swani(2579963328)","time":"1:03:54","text":["那只能玩ttk长的游戏"]},{"name":"Swani(2579963328)","time":"1:04:06","text":["这种传统fps"]},{"name":"Swani(2579963328)","time":"1:04:12","text":["后面都是一枪头"]},{"name":"我要成为怪A战碧高手(766955124)","time":"1:04:13","text":["所以我去玩2042了"]},{"name":"Swani(2579963328)","time":"1:04:19","text":["我都习惯了 反正我瓦打别人也是一枪头"]},{"name":"Swani(2579963328)","time":"1:04:22","img":["F921AE942EFD466bAE8CA5423D24872F.jpeg"]},{"name":"Swani(2579963328)","time":"1:04:40","text":["我瓦理发师只爆头 cs2被爆头爆习惯了"]},{"name":"Swani(2579963328)","time":"1:04:42","img":["6EA183E284564c8fADA94613EC078B83"]},{"name":"我要成为怪A战碧高手(766955124)","time":"1:04:59","text":["第一次玩这种"]},{"name":"Swani(2579963328)","time":"1:05:10","text":["手要稳心莫慌先瞄准再开枪"]},{"name":"Swani(2579963328)","time":"1:05:17","img":["B04CDE3948414c8691DB562E8351DF05.jpeg"]},{"name":"我要成为怪A战碧高手(766955124)","time":"1:05:21","img":["38EA903F3A9C4f9fA3B48268012E56D1.jpeg"]},{"name":"Swani(2579963328)","time":"1:05:32","text":["这种fps都是要慢慢练得"]},{"name":"兰.(513248092)","time":"1:05:36","text":["传统fps"]},{"name":"Swani(2579963328)","time":"1:05:43","text":["你一下子要玩肯定适应不过来"]},{"name":"兰.(513248092)","time":"1:05:43","text":["先唐两百个小时"]},{"name":"Swani(2579963328)","time":"1:05:51","text":["我cs1k小时了水平也就那样"]},{"name":"兰.(513248092)","time":"1:05:59","text":["再去虐人"]},{"name":"Swani(2579963328)","time":"1:06:19","text":["fps类游戏我累计时长4000小时肯定是有了"]},{"name":"Swani(2579963328)","time":"1:06:35","text":["也就那样 也不是拿这个吃饭 能让自己玩的舒服就行"]},{"name":"Swani(2579963328)","time":"1:06:39","img":["F921AE942EFD466bAE8CA5423D24872F.jpeg"]},{"name":"我要成为怪A战碧高手(766955124)","time":"1:06:41","text":["啊这"]},{"name":"Swani(2579963328)","time":"1:07:24","text":["请速速加入counter strike 2"]},{"name":"Swani(2579963328)","time":"1:07:26","img":["F921AE942EFD466bAE8CA5423D24872F.jpeg"]},{"name":"Swani(2579963328)","time":"1:07:37","text":["一打四超酷的"]},{"name":"Swani(2579963328)","time":"1:07:38","img":["F921AE942EFD466bAE8CA5423D24872F.jpeg"]},{"name":"Swani(2579963328)","time":"1:08:30","text":["这是我五一阳了"]},{"name":"Swani(2579963328)","time":"1:08:35","text":["请假五天"]},{"name":"Swani(2579963328)","time":"1:08:44","text":["打了五天cs 今年状态最好的几把"]},{"name":"Swani(2579963328)","time":"1:08:45","img":["6EA183E284564c8fADA94613EC078B83"]},{"name":"我要成为怪A战碧高手(766955124)","time":"1:08:59","img":["5A9430DED4D74197BDA9D767B4170372"]},{"name":"Swani(2579963328)","time":"1:09:04","text":["为什么我这个没人看"]},{"name":"Swani(2579963328)","time":"1:09:12","text":["这瓦视频都能入典了"]},{"name":"Swani(2579963328)","time":"1:09:14","img":["B04CDE3948414c8691DB562E8351DF05.jpeg"]},{"name":"兰.(513248092)","time":"1:09:49","img":["9474D6073FB3459fB2448748DB42285B"]},{"name":"墨彳亍(3582764281)","time":"1:49:20","text":["打瓦喊我"]},{"name":"死(2389619983)","time":"11:12:13","text":[" two thousand  forty two？"]},{"name":"我要成为怪A战碧高手(766955124)","time":"11:15:41","text":["下午"]},{"name":"我要成为怪A战碧高手(766955124)","time":"12:30:35","text":[" 现在来吗"]},{"name":"死(2389619983)","time":"12:32:29","text":["你先自己打一会"]},{"name":"死(2389619983)","time":"12:32:37","text":["我过会去拿个外卖"]},{"name":"死(2389619983)","time":"12:32:48","text":["1点10分到1点20分来吧"]},{"name":"我要成为怪A战碧高手(766955124)","time":"12:33:49","text":["ok"]},{"name":"Swani(2579963328)","time":"12:34:22","img":["2316215EDFFD4b18AFE9BCD74C9FB0B7.jpeg"]},{"name":"死(2389619983)","time":"13:33:43","text":["@我要成为怪A战碧高手"]},{"name":"死(2389619983)","time":"15:44:18","img":["5FAA10F98A5645c691E6F4FB3DD6C842"]},{"name":"咪咯(2122236603)","time":"17:06:53","img":["70DAF7EBDDBD4062AE8C7C4357BE8554"]},{"name":"死(2389619983)","time":"20:29:55","text":["该死"]},{"name":"死(2389619983)","time":"20:30:05","text":["cod20的手柄调试没做好"]},{"name":"死(2389619983)","time":"20:30:14","text":["越用越怪"]},{"name":"死(2389619983)","time":"20:30:35","text":["20手柄的手感还不如2042"]},{"name":"死(2389619983)","time":"20:30:47","text":["2042这赛季好歹更新了个真线性曲线"]},{"name":"热心市民夏先生\u0026lt;guiguidee@qq.com\u0026get;","time":"20:33:56","text":["Ywq呢"]},{"name":"热心市民夏先生\u0026lt;guiguidee@qq.com\u0026get;","time":"20:34:07","text":["他不是要在这两天大展宏图的"]},{"name":"热心市民夏先生\u0026lt;guiguidee@qq.com\u0026get;","time":"20:34:34","text":[" "]},{"name":"热心市民夏先生\u0026lt;guiguidee@qq.com\u0026get;","time":"20:34:41","text":["李在赣神魔"]},{"name":"我在往里润(1193558074)","time":"20:42:18","text":["？"]},{"name":"我在往里润(1193558074)","time":"20:42:21","text":["晚训"]},{"name":"死(2389619983)","time":"21:18:06","text":[" 你2042咋一直在线"]},{"name":"我要成为怪A战碧高手(766955124)","time":"21:18:16","text":["因为我在和别人一起玩"]},{"name":"死(2389619983)","time":"21:20:31","text":["有我的位置吗"]},{"name":"死(2389619983)","time":"21:20:33","img":["DEB1E58E66434d04B21D59191553913F.jpeg"]},{"name":"我要成为怪A战碧高手(766955124)","time":"21:20:36","text":["不知道"]},{"name":"死(2389619983)","time":"21:22:05","text":["你参考参考"]},{"name":"死(2389619983)","time":"21:39:23","text":["台式电脑受害者"]},{"name":"死(2389619983)","time":"21:39:27","text":["宿舍没电费了"]},{"name":"死(2389619983)","time":"21:39:31","text":["当场关机"]},{"name":"我要成为怪A战碧高手(766955124)","time":"21:39:34","text":["6"]},{"name":"死(2389619983)","time":"21:45:55","text":["彻底绷不住了"]},{"name":"死(2389619983)","time":"21:46:04","text":["给电脑换了个桌面"]},{"name":"死(2389619983)","time":"21:46:12","text":["我舍友看着我桌面的虹夏"]},{"name":"死(2389619983)","time":"21:46:17","text":["脱口而出一句"]},{"name":"死(2389619983)","time":"21:46:26","text":["“小埋！”"]},{"name":"我在往里润(1193558074)","time":"21:53:37","text":["好好好"]},{"name":"我在往里润(1193558074)","time":"21:53:43","text":["发色都不一样"]},{"name":"我在往里润(1193558074)","time":"21:53:47","img":["BCFFADF9387047d0B2F05E2B496887FF.jpeg"]},{"name":"热心市民夏先生\u0026lt;guiguidee@qq.com\u0026get;","time":"22:57:57","text":["？"]},{"name":"热心市民夏先生\u0026lt;guiguidee@qq.com\u0026get;","time":"22:58:12","text":["你不是应该在战斗吗"]},{"name":"我在往里润(1193558074)","time":"23:05:14","text":["我星期天六点就收假了"]},{"name":"我在往里润(1193558074)","time":"23:05:19","text":["还战斗个几把啊"]},{"name":"我在往里润(1193558074)","time":"23:05:25","img":["A1CD359FB74241b6B25C2E882C6818EE.jpeg"]},{"name":"Swani(2579963328)","time":"23:16:27","text":[" 那个可以让你录视频的那个呢"]},{"name":"Swani(2579963328)","time":"23:16:28","text":["看看"]},{"name":"Swani(2579963328)","time":"23:16:30","img":["469C81776D994ac4A2D8100DA9F2B419"]},{"name":"我在往里润(1193558074)","time":"23:23:19","text":["这个星期没约到"]},{"name":"我在往里润(1193558074)","time":"23:23:24","text":["我等下个星期"]},{"name":"死(2389619983)","time":"23:32:16","text":[" "]},{"name":"我要成为怪A战碧高手(766955124)","time":"23:32:25","text":["6"]},{"name":"Swani(2579963328)","time":"23:49:02","text":[" 我要看视频"]},{"name":"Swani(2579963328)","time":"23:49:07","img":["1BE58257C9344ef9AAD4A1149A267845"]}]